notiondb/Connector.py
notiondb/Database.py
notiondb/PropertyValues.py
notiondb/Row.py
notiondb/Schema.py
notiondb/SchemaProperty.py
notiondb/__init__.py
notion_toolkit-0.1.2.dist-info/LICENSE
notion_toolkit-0.1.2.dist-info/WHEEL
notion_toolkit-0.1.2.dist-info/METADATA
notion_toolkit-0.1.2.dist-info/RECORD
