Metadata-Version: 2.1
Name: notion-toolkit
Version: 0.1.2
Summary: A powerful object-oriented Python library for easy interaction with Notion.so databases
Home-page: https://notion-db.rtfd.io
License: GPL-3.0
Author: Matt Prodani
Author-email: mattp@nyu.edu
Requires-Python: >=3.8,<4.0
Classifier: License :: OSI Approved :: GNU General Public License v3 (GPLv3)
Classifier: Programming Language :: Python :: 3
Classifier: Programming Language :: Python :: 3.8
Classifier: Programming Language :: Python :: 3.9
Classifier: Programming Language :: Python :: 3.10
Classifier: Programming Language :: Python :: 3.11
Provides-Extra: dev
Provides-Extra: docs
Requires-Dist: autodocsumm (>=0.2.9,<0.3.0); extra == "docs"
Requires-Dist: myst-parser (>=0.18.1,<0.19.0); extra == "docs"
Requires-Dist: pandas (>=1.5.0,<2.0.0)
Requires-Dist: requests (>=2.27.1,<3.0.0)
Requires-Dist: urllib3 (>=1.25.12,<2.0.0)
Project-URL: Repository, https://github.com/mattprodani/notion-db
